makeit/__init__.py
makeit/__main__.py
makeit/main.py
makeit/make.py
makeit/py.typed
makeit/tui.py
makeit/version.py
makit-0.2.8.dist-info/LICENSE
makit-0.2.8.dist-info/METADATA
makit-0.2.8.dist-info/WHEEL
makit-0.2.8.dist-info/entry_points.txt
makit-0.2.8.dist-info/top_level.txt
makit-0.2.8.dist-info/RECORD
