Metadata-Version: 2.1
Name: makit
Version: 0.2.8
Summary: Interactive Makefile step picker
Author-email: igrek51 <igrek51.dev@gmail.com>
License: MIT
Project-URL: Homepage, https://github.com/igrek51/makeit
Classifier: Programming Language :: Python :: 3
Classifier: License :: OSI Approved :: MIT License
Classifier: Operating System :: OS Independent
Requires-Python: >=3.8
License-File: LICENSE
Requires-Dist: nuclear>=2.1.0
Requires-Dist: textual>=0.58.0
